kubemarine/__init__.py
kubemarine/__main__.py
kubemarine/admission.py
kubemarine/apparmor.py
kubemarine/apt.py
kubemarine/audit.py
kubemarine/coredns.py
kubemarine/demo.py
kubemarine/etcd.py
kubemarine/haproxy.py
kubemarine/jinja.py
kubemarine/k8s_certs.py
kubemarine/keepalived.py
kubemarine/kubernetes_accounts.py
kubemarine/modprobe.py
kubemarine/packages.py
kubemarine/py.typed
kubemarine/selinux.py
kubemarine/sysctl.py
kubemarine/system.py
kubemarine/testsuite.py
kubemarine/thirdparties.py
kubemarine/version
kubemarine/yum.py
kubemarine/core/__init__.py
kubemarine/core/action.py
kubemarine/core/annotations.py
kubemarine/core/cluster.py
kubemarine/core/connections.py
kubemarine/core/defaults.py
kubemarine/core/environment.py
kubemarine/core/errors.py
kubemarine/core/executor.py
kubemarine/core/flow.py
kubemarine/core/group.py
kubemarine/core/inventory.py
kubemarine/core/log.py
kubemarine/core/os.py
kubemarine/core/patch.py
kubemarine/core/proxytypes.py
kubemarine/core/resources.py
kubemarine/core/schema.py
kubemarine/core/static.py
kubemarine/core/summary.py
kubemarine/core/utils.py
kubemarine/core/yaml_merger.py
kubemarine/cri/__init__.py
kubemarine/cri/containerd.py
kubemarine/kubernetes/__init__.py
kubemarine/kubernetes/components.py
kubemarine/kubernetes/daemonset.py
kubemarine/kubernetes/deployment.py
kubemarine/kubernetes/object.py
kubemarine/kubernetes/replicaset.py
kubemarine/kubernetes/secrets.py
kubemarine/kubernetes/statefulset.py
kubemarine/patches/__init__.py
kubemarine/patches/pin_kubernetes_version_default.py
kubemarine/patches/software_upgrade.yaml
kubemarine/plugins/__init__.py
kubemarine/plugins/builtin.py
kubemarine/plugins/calico.py
kubemarine/plugins/kubernetes_dashboard.py
kubemarine/plugins/local_path_provisioner.py
kubemarine/plugins/manifest.py
kubemarine/plugins/nginx_ingress.py
kubemarine/plugins/yaml/calico-apiserver-v3.24.2-original.yaml
kubemarine/plugins/yaml/calico-apiserver-v3.25.1-original.yaml
kubemarine-0.44.1.dist-info/licenses/LICENSE
kubemarine-0.44.1.dist-info/METADATA
kubemarine-0.44.1.dist-info/WHEEL
kubemarine-0.44.1.dist-info/entry_points.txt
kubemarine-0.44.1.dist-info/top_level.txt
kubemarine-0.44.1.dist-info/RECORD
