Metadata-Version: 2.4
Name: kubemarine
Version: 0.44.1
Summary: Management tool for Kubernetes cluster deployment and maintenance
Home-page: https://github.com/Netcracker/KubeMarine
Author-email: Kubemarine Group <kubemarinegroup@netcracker.com>
License: Apache-2.0
Project-URL: Homepage, https://github.com/Netcracker/KubeMarine
Project-URL: Documentation, https://github.com/Netcracker/KubeMarine#documentation
Project-URL: Issues, https://github.com/Netcracker/KubeMarine/issues/
Keywords: kubernetes,devops,administration,helm
Classifier: License :: OSI Approved :: Apache Software License
Classifier: Programming Language :: Python
Classifier: Programming Language :: Python :: 3.9
Classifier: Programming Language :: Python :: 3.10
Classifier: Programming Language :: Python :: 3.11
Classifier: Programming Language :: Python :: 3.12
Classifier: Operating System :: OS Independent
Classifier: Intended Audience :: System Administrators
Classifier: Intended Audience :: Developers
Classifier: Development Status :: 5 - Production/Stable
Classifier: Environment :: Console
Requires-Python: >=3.9
License-File: LICENSE
Requires-Dist: PyYAML==6.0.*
Requires-Dist: deepmerge==1.1.*
Requires-Dist: fabric==3.2.*
Requires-Dist: jinja2==3.1.*
Requires-Dist: MarkupSafe==2.1.*
Requires-Dist: invoke==2.2.*
Requires-Dist: ruamel.yaml==0.18.*
Requires-Dist: pygelf==0.4.*
Requires-Dist: toml==0.10.*
Requires-Dist: python-dateutil==2.9.*
Requires-Dist: deepdiff==8.6.*
Requires-Dist: ordered-set==4.1.*
Requires-Dist: cryptography==44.0.1
Requires-Dist: paramiko==3.4.*
Requires-Dist: jsonschema==4.22.*
Requires-Dist: referencing==0.35.*
Requires-Dist: typing_extensions==4.11.*
Requires-Dist: pathvalidate==3.2.*
Requires-Dist: useful_types==0.2.*
Requires-Dist: packaging==24.1.*
Provides-Extra: ansible
Requires-Dist: ansible==11.4.*; extra == "ansible"
Provides-Extra: mypy
Requires-Dist: mypy==1.10.*; extra == "mypy"
Requires-Dist: types-PyYAML==6.0.*; extra == "mypy"
Requires-Dist: types-toml==0.10.*; extra == "mypy"
Requires-Dist: types-python-dateutil==2.9.*; extra == "mypy"
Requires-Dist: types-paramiko==3.4.*; extra == "mypy"
Requires-Dist: types-jsonschema==4.22.*; extra == "mypy"
Requires-Dist: types-pyinstaller==6.6.0.*; extra == "mypy"
Provides-Extra: pylint
Requires-Dist: pylint==3.1.*; extra == "pylint"
Dynamic: description
Dynamic: description-content-type
Dynamic: home-page
Dynamic: license-file
